{"chunk_definitions":[{"row":10,"row_count":1,"visible":true,"expansion_state":0,"options":{"engine":"r","include":false,"label":"unnamed-chunk-3"},"document_id":"584D80EC","chunk_id":"cs4u5fnezrjnf","chunk_label":"unnamed-chunk-1"},{"row":60,"row_count":1,"visible":true,"expansion_state":0,"options":{"engine":"r","label":"unnamed-chunk-18"},"document_id":"584D80EC","chunk_id":"cny67kiugdxi6","chunk_label":"unnamed-chunk-3"},{"row":156,"row_count":1,"visible":true,"expansion_state":0,"options":{"engine":"r","label":"unnamed-chunk-3"},"document_id":"584D80EC","chunk_id":"cwd66w6mom506","chunk_label":"unnamed-chunk-5"},{"row":410,"row_count":1,"visible":true,"expansion_state":0,"options":{"engine":"r","label":"unnamed-chunk-7"},"document_id":"584D80EC","chunk_id":"cp6ygra2ukyzc","chunk_label":"unnamed-chunk-12"},{"row":636,"row_count":1,"visible":true,"expansion_state":0,"options":{"engine":"r","label":"unnamed-chunk-2"},"document_id":"584D80EC","chunk_id":"cure5gwx9l14m","chunk_label":"unnamed-chunk-19"},{"row":652,"row_count":1,"visible":true,"expansion_state":0,"options":{"engine":"r","label":"unnamed-chunk-4"},"document_id":"584D80EC","chunk_id":"c5sws8m4xpldw","chunk_label":"unnamed-chunk-20"},{"row":695,"row_count":1,"visible":true,"expansion_state":0,"options":{"engine":"r","label":"unnamed-chunk-6"},"document_id":"584D80EC","chunk_id":"cmt1lorofsxsq","chunk_label":"unnamed-chunk-21"},{"row":702,"row_count":1,"visible":true,"expansion_state":0,"options":{"engine":"r","label":"unnamed-chunk-8"},"document_id":"584D80EC","chunk_id":"c81zowuuog5on","chunk_label":"unnamed-chunk-22"},{"row":733,"row_count":1,"visible":true,"expansion_state":0,"options":{"engine":"r","label":"unnamed-chunk-22"},"document_id":"584D80EC","chunk_id":"c0a6sieohxyv8","chunk_label":"unnamed-chunk-23"},{"row":765,"row_count":1,"visible":true,"expansion_state":0,"options":{"engine":"r","label":"unnamed-chunk-26"},"document_id":"584D80EC","chunk_id":"cl34tne3dfffd","chunk_label":"unnamed-chunk-24"},{"row":781,"row_count":1,"visible":true,"expansion_state":0,"options":{"engine":"r","label":"unnamed-chunk-21"},"document_id":"584D80EC","chunk_id":"co0wryq7tsgpd","chunk_label":"unnamed-chunk-25"},{"row":813,"row_count":1,"visible":true,"expansion_state":0,"options":{"engine":"r","label":"unnamed-chunk-12"},"document_id":"584D80EC","chunk_id":"ck1oowlne8xuo","chunk_label":"unnamed-chunk-26"},{"row":839,"row_count":1,"visible":true,"expansion_state":0,"options":{"engine":"r","label":"unnamed-chunk-16"},"document_id":"584D80EC","chunk_id":"cu2d4lqdjjr2u","chunk_label":"unnamed-chunk-27"},{"row":844,"row_count":1,"visible":true,"expansion_state":0,"options":{"engine":"r","label":"unnamed-chunk-2"},"document_id":"584D80EC","chunk_id":"cwxysii6wzha2","chunk_label":"unnamed-chunk-28"},{"row":854,"row_count":1,"visible":true,"expansion_state":0,"options":{"engine":"r","label":"unnamed-chunk-9"},"document_id":"584D80EC","chunk_id":"ce1wnu8y7s9ws","chunk_label":"unnamed-chunk-29"},{"row":919,"row_count":1,"visible":true,"expansion_state":0,"options":{"engine":"r","label":"unnamed-chunk-18"},"document_id":"584D80EC","chunk_id":"c5nhp85i5np3s","chunk_label":"unnamed-chunk-30"},{"row":984,"row_count":1,"visible":true,"expansion_state":0,"options":{"engine":"r","label":"unnamed-chunk-11"},"document_id":"584D80EC","chunk_id":"ccifihisqkhj5","chunk_label":"unnamed-chunk-31"},{"row":1015,"row_count":1,"visible":true,"expansion_state":0,"options":{"engine":"r","label":"unnamed-chunk-12"},"document_id":"584D80EC","chunk_id":"cto730wzqf1ji","chunk_label":"unnamed-chunk-32"},{"row":1024,"row_count":1,"visible":true,"expansion_state":0,"options":{"engine":"r","label":"unnamed-chunk-13"},"document_id":"584D80EC","chunk_id":"cbdv5refn6rkd","chunk_label":"unnamed-chunk-33"},{"row":1028,"row_count":1,"visible":true,"expansion_state":0,"options":{"engine":"r","label":"unnamed-chunk-6"},"document_id":"584D80EC","chunk_id":"ccm96g0d9men5","chunk_label":"unnamed-chunk-34"},{"row":1041,"row_count":1,"visible":true,"expansion_state":0,"options":{"engine":"r","label":"unnamed-chunk-15"},"document_id":"584D80EC","chunk_id":"ch35y9wiwtbas","chunk_label":"unnamed-chunk-35"},{"row":1072,"row_count":1,"visible":true,"expansion_state":0,"options":{"engine":"r","label":"unnamed-chunk-16"},"document_id":"584D80EC","chunk_id":"c3ftik75u32gi","chunk_label":"unnamed-chunk-36"},{"row":1103,"row_count":1,"visible":true,"expansion_state":0,"options":{"engine":"r","label":"unnamed-chunk-5"},"document_id":"584D80EC","chunk_id":"c9kmi1go7eexl","chunk_label":"unnamed-chunk-37"},{"row":1112,"row_count":1,"visible":true,"expansion_state":0,"options":{"engine":"r","label":"unnamed-chunk-8"},"document_id":"584D80EC","chunk_id":"cw56xwnsi4fj1","chunk_label":"unnamed-chunk-38"},{"row":1138,"row_count":1,"visible":true,"expansion_state":0,"options":{"engine":"r","label":"unnamed-chunk-7"},"document_id":"584D80EC","chunk_id":"cjor9umrqt8uc","chunk_label":"unnamed-chunk-39"},{"row":1165,"row_count":1,"visible":true,"expansion_state":0,"options":{"engine":"r","label":"unnamed-chunk-8"},"document_id":"584D80EC","chunk_id":"c9o2nv7l6ytcx","chunk_label":"unnamed-chunk-40"},{"row":1209,"row_count":1,"visible":true,"expansion_state":0,"options":{"engine":"r","label":"unnamed-chunk-73"},"document_id":"584D80EC","chunk_id":"cy08d7r8ckppi","chunk_label":"unnamed-chunk-42"},{"row":1225,"row_count":1,"visible":true,"expansion_state":0,"options":{"engine":"r","label":"unnamed-chunk-9"},"document_id":"584D80EC","chunk_id":"cvb20v6u2nl2h","chunk_label":"unnamed-chunk-43"},{"row":1254,"row_count":1,"visible":true,"expansion_state":0,"options":{"engine":"r","label":"unnamed-chunk-25"},"document_id":"584D80EC","chunk_id":"czl6ecilvopu9","chunk_label":"unnamed-chunk-44"},{"row":1308,"row_count":1,"visible":true,"expansion_state":0,"options":{"engine":"r","label":"unnamed-chunk-8"},"document_id":"584D80EC","chunk_id":"ck7xf596w0c2v","chunk_label":"unnamed-chunk-46"},{"row":1320,"row_count":1,"visible":true,"expansion_state":0,"options":{"engine":"r","label":"unnamed-chunk-19"},"document_id":"584D80EC","chunk_id":"cxzfjtgjon1pc","chunk_label":"unnamed-chunk-47"},{"row":1344,"row_count":1,"visible":true,"expansion_state":0,"options":{"engine":"r","label":"unnamed-chunk-16"},"document_id":"584D80EC","chunk_id":"c77asmivllw04","chunk_label":"unnamed-chunk-48"},{"row":1348,"row_count":1,"visible":true,"expansion_state":0,"options":{"engine":"r","label":"unnamed-chunk-20"},"document_id":"584D80EC","chunk_id":"cyhy8y3hbiny8","chunk_label":"unnamed-chunk-49"},{"row":1368,"row_count":1,"visible":true,"expansion_state":0,"options":{"engine":"r","label":"unnamed-chunk-62"},"document_id":"584D80EC","chunk_id":"cbmevmiw5bdrs","chunk_label":"unnamed-chunk-50"},{"row":1377,"row_count":1,"visible":true,"expansion_state":0,"options":{"engine":"r","label":"unnamed-chunk-64"},"document_id":"584D80EC","chunk_id":"cvcv9gqzxbe0c","chunk_label":"unnamed-chunk-51"},{"row":1388,"row_count":1,"visible":true,"expansion_state":0,"options":{"engine":"r","label":"unnamed-chunk-59"},"document_id":"584D80EC","chunk_id":"c211tbkc0u1yh","chunk_label":"unnamed-chunk-52"},{"row":1392,"row_count":1,"visible":true,"expansion_state":0,"options":{"engine":"r","label":"unnamed-chunk-65"},"document_id":"584D80EC","chunk_id":"c5841u7csgb23","chunk_label":"unnamed-chunk-53"},{"row":1418,"row_count":1,"visible":true,"expansion_state":0,"options":{"engine":"r","label":"unnamed-chunk-17"},"document_id":"584D80EC","chunk_id":"cmaaf051u6ney","chunk_label":"unnamed-chunk-54"},{"row":1440,"row_count":1,"visible":true,"expansion_state":0,"options":{"engine":"r","label":"unnamed-chunk-18"},"document_id":"584D80EC","chunk_id":"ca88jrm7i7aag","chunk_label":"unnamed-chunk-55"}],"doc_write_time":1690212972}